{"drawer":{"avatarEnabled":false,"enabled":false,"list":[],"wallpaperEnabled":false},"fab":{"enabled":false,"src":"add"},"toolbar":{"autoHide":false,"enabled":true,"homeButtonEnabled":true,"menus":[],"searchEnabled":true,"style":0,"subTitle":"小说爬虫搜索引擎","title":"小鑫工具箱2.0"},"viewPager":{"indGravity":0,"indStyle":0,"offscreenPageLimit":0,"pages":[{"indTitle":"main","url":"https://jinbilianshao.github.io/xiaoxin"}],"transformer":0,"userInputEnabled":false},"webView":{"colorMode":false,"darkMode":1,"javaScriptEnabled":true,"openOtherPageWays":2,"pcMode":false,"userAgent":"default"}}